osipyapi/__init__.py
osipyapi/__version__.py
osipyapi/_batch.py
osipyapi/_channel.py
osipyapi/_client.py
osipyapi/_enums.py
osipyapi/_exceptions.py
osipyapi/_models.py
osipyapi/_types.py
osipyapi/_util.py
osipyapi/py.typed
osipyapi/_api/__init__.py
osipyapi/_api/_api.py
osipyapi/_api/_controllers/__init__.py
osipyapi/_api/_controllers/_assetdatabase.py
osipyapi/_api/_controllers/_assetserver.py
osipyapi/_api/_controllers/_attribute.py
osipyapi/_api/_controllers/_channel.py
osipyapi/_api/_controllers/_dataserver.py
osipyapi/_api/_controllers/_element.py
osipyapi/_api/_controllers/_point.py
osipyapi/_api/_controllers/_search.py
osipyapi/_api/_controllers/_stream.py
osipyapi/_api/_controllers/_streamset.py
osipyapi-0.1.3.dist-info/LICENSE
osipyapi-0.1.3.dist-info/METADATA
osipyapi-0.1.3.dist-info/WHEEL
osipyapi-0.1.3.dist-info/top_level.txt
osipyapi-0.1.3.dist-info/RECORD
