Metadata-Version: 2.1
Name: osipyapi
Version: 0.1.3
Summary: Async client for OSIsoft's PI Web API
Home-page: https://github.com/newvicx/osipyapi
Author: Chris Newville
Author-email: chrisnewville1396@gmail.com
License: MIT
Project-URL: Changelog, https://github.com/newvicx/osipyapi/blob/master/CHANGELOG.md
Project-URL: Source, https://github.com/newvicx/osipyapi
Classifier: Development Status :: 4 - Beta
Classifier: Environment :: Web Environment
Classifier: Intended Audience :: Developers
Classifier: License :: OSI Approved :: MIT License
Classifier: Operating System :: Microsoft :: Windows
Classifier: Topic :: Internet :: WWW/HTTP
Classifier: Framework :: AsyncIO
Classifier: Programming Language :: Python :: 3
Classifier: Programming Language :: Python :: 3.10
Classifier: Programming Language :: Python :: 3 :: Only
Requires-Python: >=3.10
License-File: LICENSE
Requires-Dist: uhttp (>=0.2.2)
Requires-Dist: uhttp-negotiate (>=0.1.1)
Requires-Dist: polars (>=0.13.52)
Requires-Dist: pandas (>=1.4.3)
Requires-Dist: pyarrow (>=8.0.0)
Requires-Dist: orjson (>=3.7.7)
Requires-Dist: rrtarget (>=0.1.0)
